CommonLib/Common.py
CommonLib/__init__.py
CommonLib_AV-0.1.1.dist-info/LICENSE.txt
CommonLib_AV-0.1.1.dist-info/METADATA
CommonLib_AV-0.1.1.dist-info/WHEEL
CommonLib_AV-0.1.1.dist-info/top_level.txt
CommonLib_AV-0.1.1.dist-info/RECORD
