Metadata-Version: 2.1
Name: CommonLib-AV
Version: 0.1.1
Summary: Common methods for google bigquery
Home-page: https://github.com/pypa/sampleproject
Author: Abhishek Verma
Author-email: 28a.v10@gmail.com
License: UNKNOWN
Project-URL: Bug Tracker, https://github.com/pypa/sampleproject/issues
Platform: UNKNOWN
Classifier: Programming Language :: Python :: 3
Classifier: License :: OSI Approved :: MIT License
Classifier: Operating System :: OS Independent
Requires-Python: >=3.6
License-File: LICENSE.txt
